{"type": "Feature", "id": 12514708, "properties": {"woe:id": 12514708, "woe:parent_id": 1364685, "woe:name": "Toamasina Airport", "woe:placetype": 14, "woe:placetype_name": "Airport", "woe:lang": "ENG", "iso:country": "MG", "meta:provider": ["geoplanet:7.3.1", "geoplanet:7.3.2", "geoplanet:7.4.0", "geoplanet:7.4.1", "geoplanet:7.5.1", "geoplanet:7.5.2", "geoplanet:7.6.0", "geoplanet:7.8.1", "geoplanet:7.9.0", "geoplanet:7.10.0", "geoplanet:8.0.0", "woeplanet:8.0.0"], "meta:indexed": "2020-08-20T20:57:40.344398", "woe:alias_ENG_V": ["TMM Airport", "TMM"], "meta:updated": "2020-08-22T01:58:53.537259", "woe:hierarchy": {"continent": 24865670, "country": 23424883, "town": 0, "planet": 1, "county": 23706579, "suburb": 0, "state": 2346149, "region": 0, "localadmin": 0}, "woe:timezone_id": 28350925, "woe:hash": "mhg0gzy4ddmk", "woe:centroid": [49.391899, -18.1064], "geom:latitude": -18.1064, "geom:longitude": 49.391899, "geom:hash": "mhg0gzy4ddmk", "woe:latitude": -18.1064, "geom:centroid": [49.391899, -18.1064], "woe:longitude": 49.391899, "woe:repo": "woeplanet-airport-mg"}, "geometry": {"coordinates": [49.391899, -18.1064], "type": "Point"}}