{"type": "Feature", "id": 12514704, "geometry": {"type": "Point", "coordinates": [43.374199, -21.750601]}, "properties": {"woe:id": 12514704, "woe:parent_id": 1363521, "woe:name": "Morombe Airport", "woe:placetype": 14, "woe:placetype_name": "Airport", "woe:lang": "ENG", "iso:country": "MG", "meta:provider": ["geoplanet:7.3.1", "geoplanet:7.3.2", "geoplanet:7.4.0", "geoplanet:7.4.1", "geoplanet:7.5.1", "geoplanet:7.5.2", "geoplanet:7.6.0", "geoplanet:7.8.1", "geoplanet:7.9.0", "geoplanet:7.10.0", "geoplanet:8.0.0", "woeplanet:8.0.0"], "meta:indexed": "2020-08-20T20:57:40.340973", "woe:alias_ENG_V": ["MXM Airport", "MXM"], "meta:updated": "2020-10-14T11:26:52.970466", "woe:hierarchy": {"continent": 24865670, "country": 23424883, "town": 0, "planet": 1, "county": 23706571, "suburb": 0, "state": 2346151, "region": 0, "localadmin": 0}, "woe:timezone_id": 28350925, "woe:hash": "kunu702js44g", "woe:centroid": [43.374199, -21.750601], "geom:latitude": -21.750601, "geom:longitude": 43.374199, "geom:hash": "kunu702js44g", "woe:latitude": -21.750601, "geom:centroid": [43.374199, -21.750601], "woe:longitude": 43.374199, "woe:repo": "woeplanet-airport-mg", "geom:area": 0.0, "woe:scale": 19}}