{"type": "Feature", "id": 12514686, "properties": {"woe:id": 12514686, "woe:parent_id": 1492153, "woe:name": "Anahidrano Airport", "woe:placetype": 14, "woe:placetype_name": "Airport", "woe:lang": "ENG", "iso:country": "MG", "meta:provider": ["geoplanet:7.3.1", "geoplanet:7.3.2", "geoplanet:7.4.0", "geoplanet:7.4.1", "geoplanet:7.5.1", "geoplanet:7.5.2", "geoplanet:7.6.0", "geoplanet:7.8.1", "geoplanet:7.9.0", "geoplanet:7.10.0", "geoplanet:8.0.0", "woeplanet:8.0.0"], "meta:indexed": "2020-08-20T20:57:40.326009", "meta:updated": "2020-08-22T01:58:53.530142", "woe:hierarchy": {"continent": 24865670, "country": 23424883, "town": 0, "planet": 1, "county": 23706602, "suburb": 0, "state": 2346148, "region": 0, "localadmin": 0}, "woe:timezone_id": 28350925, "woe:hash": "mj64d1ns1gnt", "woe:centroid": [47.909401, -15.0231], "geom:latitude": -15.0231, "geom:longitude": 47.909401, "geom:hash": "mj64d1ns1gnt", "woe:latitude": -15.0231, "geom:centroid": [47.909401, -15.0231], "woe:longitude": 47.909401, "woe:repo": "woeplanet-airport-mg"}, "geometry": {"coordinates": [47.909401, -15.0231], "type": "Point"}}